{
	"id": "I-693 ",
	"title": "I-693 | Report of Immigration Medical Examination and Vaccination Record",
	"link": "https://www.uscis.gov/i-693",
	"description": "If you are applying for adjustment status to become a lawful permanent resident, use this form to establish that you are not inadmissible to the United States on public health grounds.",
	"file-online": false,
	"forms": [
		{
			"id": "i-693.pdf",
			"title": "Form I-693",
			"link": "https://www.uscis.gov/sites/default/files/document/forms/i-693.pdf",
			"description": "(PDF, 684.28 KB)",
			"file-online": false
		},
		{
			"id": "i-693instr.pdf",
			"title": "Instructions for Form I-693",
			"link": "https://www.uscis.gov/sites/default/files/document/forms/i-693instr.pdf",
			"description": "(PDF, 444.74 KB)",
			"file-online": false
		}
	]
}